<annotation>
	<folder>stop</folder>
	<filename>stop_69.jpg</filename>
	<path>/home/fu/PycharmProjects/nanodet_cigar/train_data/train/img/stop_69.jpg</path>
	<source>
		<database>Unknown</database>
	</source>
	<size>
		<width>224</width>
		<height>224</height>
		<depth>3</depth>
	</size>
	<segmented>0</segmented>
	<object>
		<name>stop</name>
		<pose>Unspecified</pose>
		<truncated>0</truncated>
		<difficult>0</difficult>
		<bndbox>
			<xmin>75</xmin>
			<ymin>6</ymin>
			<xmax>101</xmax>
			<ymax>63</ymax>
		</bndbox>
	</object>
</annotation>
